{
  "type_description_msg": {
    "type_description": {
      "type_name": "dobot_msgs_v4/srv/BrakeControl_Event",
      "fields": [
        {
          "name": "info",
          "type": {
            "type_id": 1,
            "capacity": 0,
            "string_capacity": 0,
            "nested_type_name": "service_msgs/msg/ServiceEventInfo"
          },
          "default_value": ""
        },
        {
          "name": "request",
          "type": {
            "type_id": 97,
            "capacity": 1,
            "string_capacity": 0,
            "nested_type_name": "dobot_msgs_v4/srv/BrakeControl_Request"
          },
          "default_value": ""
        },
        {
          "name": "response",
          "type": {
            "type_id": 97,
            "capacity": 1,
            "string_capacity": 0,
            "nested_type_name": "dobot_msgs_v4/srv/BrakeControl_Response"
          },
          "default_value": ""
        }
      ]
    },
    "referenced_type_descriptions": [
      {
        "type_name": "builtin_interfaces/msg/Time",
        "fields": [
          {
            "name": "sec",
            "type": {
              "type_id": 6,
              "capacity": 0,
              "string_capacity": 0,
              "nested_type_name": ""
            },
            "default_value": ""
          },
          {
            "name": "nanosec",
            "type": {
              "type_id": 7,
              "capacity": 0,
              "string_capacity": 0,
              "nested_type_name": ""
            },
            "default_value": ""
          }
        ]
      },
      {
        "type_name": "dobot_msgs_v4/srv/BrakeControl_Request",
        "fields": [
          {
            "name": "axis_id",
            "type": {
              "type_id": 6,
              "capacity": 0,
              "string_capacity": 0,
              "nested_type_name": ""
            },
            "default_value": ""
          },
          {
            "name": "value",
            "type": {
              "type_id": 6,
              "capacity": 0,
              "string_capacity": 0,
              "nested_type_name": ""
            },
            "default_value": ""
          }
        ]
      },
      {
        "type_name": "dobot_msgs_v4/srv/BrakeControl_Response",
        "fields": [
          {
            "name": "res",
            "type": {
              "type_id": 6,
              "capacity": 0,
              "string_capacity": 0,
              "nested_type_name": ""
            },
            "default_value": ""
          }
        ]
      },
      {
        "type_name": "service_msgs/msg/ServiceEventInfo",
        "fields": [
          {
            "name": "event_type",
            "type": {
              "type_id": 3,
              "capacity": 0,
              "string_capacity": 0,
              "nested_type_name": ""
            },
            "default_value": ""
          },
          {
            "name": "stamp",
            "type": {
              "type_id": 1,
              "capacity": 0,
              "string_capacity": 0,
              "nested_type_name": "builtin_interfaces/msg/Time"
            },
            "default_value": ""
          },
          {
            "name": "client_gid",
            "type": {
              "type_id": 51,
              "capacity": 16,
              "string_capacity": 0,
              "nested_type_name": ""
            },
            "default_value": ""
          },
          {
            "name": "sequence_number",
            "type": {
              "type_id": 8,
              "capacity": 0,
              "string_capacity": 0,
              "nested_type_name": ""
            },
            "default_value": ""
          }
        ]
      }
    ]
  },
  "type_hashes": [
    {
      "type_name": "dobot_msgs_v4/srv/BrakeControl_Event",
      "hash_string": "RIHS01_c9bf0f430704564ba9ebf827d5735564e32d4d0feea841c6b25e8ea5ea57df0d"
    },
    {
      "type_name": "builtin_interfaces/msg/Time",
      "hash_string": "RIHS01_b106235e25a4c5ed35098aa0a61a3ee9c9b18d197f398b0e4206cea9acf9c197"
    },
    {
      "type_name": "dobot_msgs_v4/srv/BrakeControl_Request",
      "hash_string": "RIHS01_90c6b0d666aa3b4526c5ab9c6d7fcb115be90a2d5bff047948da63fb966d2305"
    },
    {
      "type_name": "dobot_msgs_v4/srv/BrakeControl_Response",
      "hash_string": "RIHS01_ada7c75c6d34fd91b88196e4b4cef50acc491b13631a096abce2ca8ba30b864f"
    },
    {
      "type_name": "service_msgs/msg/ServiceEventInfo",
      "hash_string": "RIHS01_41bcbbe07a75c9b52bc96bfd5c24d7f0fc0a08c0cb7921b3373c5732345a6f45"
    }
  ]
}