{
  "type_description_msg": {
    "type_description": {
      "type_name": "dobot_msgs_v4/srv/User_Request",
      "fields": [
        {
          "name": "index",
          "type": {
            "type_id": 6,
            "capacity": 0,
            "string_capacity": 0,
            "nested_type_name": ""
          },
          "default_value": ""
        }
      ]
    },
    "referenced_type_descriptions": []
  },
  "type_hashes": [
    {
      "type_name": "dobot_msgs_v4/srv/User_Request",
      "hash_string": "RIHS01_f33d947fe9e734a875da8ce3e753ff2cd4da1a067a9e17e74350e08f96e74342"
    }
  ]
}